cm_generator/__init__.py
cm_generator/cli.py
cm_generator/generator.py
cm_generator/handler.py
cm_generator-0.0.2.dist-info/entry_points.txt
cm_generator-0.0.2.dist-info/LICENSE
cm_generator-0.0.2.dist-info/METADATA
cm_generator-0.0.2.dist-info/WHEEL
cm_generator-0.0.2.dist-info/RECORD
